undent/__init__.py
undent/__version__.py
undent/api.py
undent-0.2.dist-info/METADATA
undent-0.2.dist-info/RECORD
undent-0.2.dist-info/WHEEL
undent-0.2.dist-info/top_level.txt
